<?xml version="1.0" encoding="UTF-8"?>
<persistence>
   <persistence-unit name="ManagerSecurityPU">
   	  <provider>org.hibernate.ejb.HibernatePersistence</provider>
      <jta-data-source>java:jboss/BossySchemaDS</jta-data-source>
      <class>dev.security.entities.User</class> 
      <properties>
            <property name="hibernate.dialect" value="org.hibernate.dialect.PostgreSQLDialect"/>
            <property name="hibernate.connection.driver_class" value="org.postgresql.Driver"/>
        </properties> 
   </persistence-unit>
</persistence>